tests/__init__.py
tests/fixtures.py
tests/test_fields.py
tests/test_queryset.py
tests/test_table.py
tests/test_user_table_creation.py
tiny_sqlite_orm/__init__.py
tiny_sqlite_orm/database.py
tiny_sqlite_orm/field.py
tiny_sqlite_orm/queryset.py
tiny_sqlite_orm/record.py
tiny_sqlite_orm/table.py
tiny_sqlite_orm/utils.py
tiny_sqlite_orm-1.2.3.dist-info/LICENSE
tiny_sqlite_orm-1.2.3.dist-info/METADATA
tiny_sqlite_orm-1.2.3.dist-info/WHEEL
tiny_sqlite_orm-1.2.3.dist-info/top_level.txt
tiny_sqlite_orm-1.2.3.dist-info/RECORD
