Metadata-Version: 2.1
Name: tiny_sqlite_orm
Version: 1.2.3
Summary: A simple ORM for SQLite databases in Python
Home-page: https://github.com/Felifelps/tiny_sqlite_orm
Author: Felifelps
Author-email: felifelps.dev@gmail.com
Classifier: Programming Language :: Python :: 3
Classifier: License :: OSI Approved :: MIT License
Classifier: Operating System :: OS Independent
Requires-Python: >=3.6
License-File: LICENSE
